indico_chat/__init__.py
indico_chat/blueprint.py
indico_chat/forms.py
indico_chat/notifications.py
indico_chat/plugin.py
indico_chat/util.py
indico_chat/views.py
indico_chat/xmpp.py
indico_chat/controllers/__init__.py
indico_chat/controllers/base.py
indico_chat/controllers/event.py
indico_chat/controllers/logs.py
indico_chat/controllers/management.py
indico_chat/migrations/.no-headers
indico_chat/migrations/20170630_1551_3888761f35f7_create_tables.py
indico_chat/models/__init__.py
indico_chat/models/chatrooms.py
indico_chat/static/dist/manifest.json
indico_chat/static/dist/css/main.51427ca1.css
indico_chat/static/dist/css/main.51427ca1.css.map
indico_chat/static/dist/js/main.8a00e183.bundle.js
indico_chat/static/dist/js/main.8a00e183.bundle.js.map
indico_chat/templates/event_header.html
indico_chat/templates/event_page.html
indico_chat/templates/how_to_connect.html
indico_chat/templates/manage_event.html
indico_chat/templates/manage_event_edit.html
indico_chat/templates/manage_event_logs.html
indico_chat/templates/emails/added.txt
indico_chat/templates/emails/attached.txt
indico_chat/templates/emails/base.txt
indico_chat/templates/emails/created.txt
indico_chat/templates/emails/deleted.txt
indico_chat/templates/emails/modified.txt
indico_chat/translations/messages-js.pot
indico_chat/translations/messages.pot
indico_chat/translations/fr_FR/LC_MESSAGES/messages-js.po
indico_chat/translations/fr_FR/LC_MESSAGES/messages.mo
indico_chat/translations/fr_FR/LC_MESSAGES/messages.po
indico_plugin_chat-2.2.dist-info/METADATA
indico_plugin_chat-2.2.dist-info/WHEEL
indico_plugin_chat-2.2.dist-info/entry_points.txt
indico_plugin_chat-2.2.dist-info/top_level.txt
indico_plugin_chat-2.2.dist-info/RECORD
