Metadata-Version: 2.1
Name: indico-plugin-chat
Version: 2.2
Summary: XMPP chat integration for Indico
Home-page: https://github.com/indico/indico-plugins
Author: Indico Team
Author-email: indico-team@cern.ch
License: MIT
Platform: UNKNOWN
Classifier: Environment :: Plugins
Classifier: Environment :: Web Environment
Classifier: License :: OSI Approved :: MIT License
Classifier: Programming Language :: Python :: 2.7
Classifier: Topic :: Communications :: Chat
Requires-Dist: indico (>=2.2.dev0)
Requires-Dist: sleekxmpp
